google/fhir/views/__init__.py
google/fhir/views/_view_config.py
google/fhir/views/_view_config_test.py
google/fhir/views/_views_test_base.py
google/fhir/views/bigquery_runner.py
google/fhir/views/bigquery_runner_test.py
google/fhir/views/bigquery_value_set_manager.py
google/fhir/views/bigquery_value_set_manager_test.py
google/fhir/views/column_expression_builder.py
google/fhir/views/column_expression_builder_test.py
google/fhir/views/fhir_search_runner.py
google/fhir/views/fhir_search_runner_test.py
google/fhir/views/r4.py
google/fhir/views/r4_test.py
google/fhir/views/runner_utils.py
google/fhir/views/runner_utils_test.py
google/fhir/views/spark_runner.py
google/fhir/views/spark_runner_test.py
google/fhir/views/spark_value_set_manager.py
google/fhir/views/spark_value_set_manager_test.py
google/fhir/views/views.py
google_fhir_views-0.11.0.dist-info/METADATA
google_fhir_views-0.11.0.dist-info/WHEEL
google_fhir_views-0.11.0.dist-info/top_level.txt
google_fhir_views-0.11.0.dist-info/RECORD
